todofinder/__init__.py
todofinder/__main__.py
todofinder/plugins.py
todofinder-1.2.0.dist-info/METADATA
todofinder-1.2.0.dist-info/WHEEL
todofinder-1.2.0.dist-info/top_level.txt
todofinder-1.2.0.dist-info/RECORD
